{
  "snapshots_due": [
    "1h",
    "6h",
    "24h",
    "48h",
    "7d"
  ],
  "snapshots_collected": [],
  "day": 112,
  "linkedin": {
    "published_at": "2026-04-22T17:50:42.066Z",
    "post_url": "https://www.linkedin.com/feed/update/urn:li:activity:7452775831548112896/",
    "has_image": true,
    "image_count": 5,
    "has_first_comment": true
  },
  "facebook": {
    "published_at": "2026-04-22T17:50:52.891Z",
    "post_url": "https://www.facebook.com/andrew.wang.716/posts/26533765706287358",
    "has_image": true,
    "image_count": 5,
    "has_first_comment": true
  },
  "threads": {
    "published_at": "2026-04-22T17:58:24.872Z",
    "post_url": "https://www.threads.com/@andrew54068/post/DXcXMSOGoZM",
    "post_count": 2,
    "topic": "AI",
    "has_image": true
  }
}
